rexia_ai/__init__.py
rexia_ai/agencies/__init__.py
rexia_ai/agencies/agency.py
rexia_ai/agents/__init__.py
rexia_ai/agents/agent.py
rexia_ai/agents/component.py
rexia_ai/agents/routers/__init__.py
rexia_ai/agents/routers/task_complexity_router.py
rexia_ai/agents/workers/__init__.py
rexia_ai/agents/workers/code.py
rexia_ai/agents/workers/code_tool.py
rexia_ai/agents/workers/finalise.py
rexia_ai/agents/workers/plan.py
rexia_ai/agents/workers/tdd.py
rexia_ai/agents/workers/team_work.py
rexia_ai/agents/workers/tool.py
rexia_ai/agents/workers/work.py
rexia_ai/base/__init__.py
rexia_ai/base/base_tool.py
rexia_ai/base/base_worker.py
rexia_ai/base/base_workflow.py
rexia_ai/common/__init__.py
rexia_ai/common/collaboration_channel.py
rexia_ai/common/containerised_code_tester.py
rexia_ai/common/containerised_tool_runner.py
rexia_ai/common/task_status.py
rexia_ai/common/utility.py
rexia_ai/llms/__init__.py
rexia_ai/llms/rexia_ai_openai.py
rexia_ai/structure/__init__.py
rexia_ai/structure/output_structure.py
rexia_ai/structure/rexia_ai_response.py
rexia_ai/tools/__init__.py
rexia_ai/tools/alpha_vantage.py
rexia_ai/tools/google_search.py
rexia_ai/tools/image_analysis.py
rexia_ai/tools/query_knowledge_base.py
rexia_ai/tools/youtube_video_analysis.py
rexia_ai/workflows/__init__.py
rexia_ai/workflows/code_tool_workflow.py
rexia_ai/workflows/code_workflow.py
rexia_ai/workflows/collaboration_workflow.py
rexia_ai/workflows/reflect_workflow.py
rexia_ai/workflows/simple_tool_workflow.py
rexia_ai/workflows/tdd_workflow.py
rexia_ai-0.3.5.5.dist-info/LICENSE
rexia_ai-0.3.5.5.dist-info/METADATA
rexia_ai-0.3.5.5.dist-info/WHEEL
rexia_ai-0.3.5.5.dist-info/top_level.txt
rexia_ai-0.3.5.5.dist-info/RECORD
