Metadata-Version: 2.1
Name: rexia_ai
Version: 0.3.5.5
Summary: ReXia.AI: An advanced AI framework for agentic processes
Home-page: https://github.com/RexiaAI/rexia_ai/tree/master
Author: Robyn Le Sueur
Author-email: robyn.lesueur@googlemail.com
Classifier: Development Status :: 3 - Alpha
Classifier: Intended Audience :: Developers
Classifier: License :: OSI Approved :: Apache Software License
Classifier: Programming Language :: Python :: 3
Classifier: Programming Language :: Python :: 3.8
Classifier: Programming Language :: Python :: 3.9
Classifier: Programming Language :: Python :: 3.10
Requires-Python: >=3.8
License-File: LICENSE
Requires-Dist: docker >=7.1.0
Requires-Dist: gradio ==4.39.0
Requires-Dist: json5 ==0.9.25
Requires-Dist: json-repair ==0.25.3
Requires-Dist: langchain-community <0.3.0,>=0.2.9
Requires-Dist: langchain-google-community <1.1.0,>=1.0.7
Requires-Dist: langchain-openai ==0.1.17
Requires-Dist: llmware ==0.3.0
Requires-Dist: moviepy ==1.0.3
Requires-Dist: openai ==1.37.0
Requires-Dist: opencv-python ==4.10.0.82
Requires-Dist: opencv-python-headless ==4.10.0.82
Requires-Dist: pydantic ==2.8.2
Requires-Dist: pytube ==15.0.0
Requires-Dist: Requests ==2.32.3
Requires-Dist: setuptools ==69.5.1
Requires-Dist: tenacity <9.0.0,>=8.3.0
Requires-Dist: transformers ==4.41.2
